shippinglabel/__init__.py
shippinglabel/checksum.py
shippinglabel/classifiers.py
shippinglabel/py.typed
shippinglabel/requirements.py
shippinglabel/sdist.py
shippinglabel/_vendor/__init__.py
shippinglabel/_vendor/requirements.txt
shippinglabel/_vendor/trove_classifiers/LICENSE
shippinglabel/_vendor/trove_classifiers/__init__.py
shippinglabel/_vendor/trove_classifiers/__main__.py
shippinglabel/_vendor/trove_classifiers/py.typed
shippinglabel-2.3.0.dist-info/METADATA
shippinglabel-2.3.0.dist-info/WHEEL
shippinglabel-2.3.0.dist-info/licenses/LICENSE
shippinglabel-2.3.0.dist-info/RECORD
