Metadata-Version: 2.4
Name: shippinglabel
Version: 2.3.0
Summary: Utilities for handling packages.
Project-URL: Homepage, https://github.com/domdfcoding/shippinglabel
Project-URL: Issue Tracker, https://github.com/domdfcoding/shippinglabel/issues
Project-URL: Source Code, https://github.com/domdfcoding/shippinglabel
Project-URL: Documentation, https://shippinglabel.readthedocs.io/en/latest
Author-email: Dominic Davis-Foster <dominic@davis-foster.co.uk>
License: Copyright (c) 2020-2022 Dominic Davis-Foster
License-File: LICENSE
Keywords: conda,packaging,pypi,requirements
Classifier: Development Status :: 5 - Production/Stable
Classifier: Intended Audience :: Developers
Classifier: License :: OSI Approved :: MIT License
Classifier: Operating System :: OS Independent
Classifier: Programming Language :: Python
Classifier: Programming Language :: Python :: 3 :: Only
Classifier: Programming Language :: Python :: 3.7
Classifier: Programming Language :: Python :: 3.8
Classifier: Programming Language :: Python :: 3.9
Classifier: Programming Language :: Python :: 3.10
Classifier: Programming Language :: Python :: 3.11
Classifier: Programming Language :: Python :: 3.12
Classifier: Programming Language :: Python :: 3.13
Classifier: Programming Language :: Python :: Implementation :: CPython
Classifier: Programming Language :: Python :: Implementation :: PyPy
Classifier: Topic :: Software Development :: Libraries :: Python Modules
Classifier: Topic :: System :: Archiving :: Packaging
Classifier: Typing :: Typed
Requires-Python: >=3.7
Requires-Dist: dist-meta>=0.1.2
Requires-Dist: dom-toml>=0.2.2
Requires-Dist: domdf-python-tools>=3.1.0
Requires-Dist: packaging>=20.9
Requires-Dist: typing-extensions>=3.7.4.3
